giextractor.py
google_image_extractor-1.0.4b1.dist-info/DESCRIPTION.rst
google_image_extractor-1.0.4b1.dist-info/METADATA
google_image_extractor-1.0.4b1.dist-info/RECORD
google_image_extractor-1.0.4b1.dist-info/WHEEL
google_image_extractor-1.0.4b1.dist-info/metadata.json
google_image_extractor-1.0.4b1.dist-info/top_level.txt
