Metadata-Version: 2.0
Name: google-image-extractor
Version: 1.0.4b1
Summary: Utility to search and download images from google image search
Home-page: https://github.com/Stryker0301/google-image-extractor
Author: Sagar R. Jadhav
Author-email: sagarrjadhav.03@gmail.com
License: UNKNOWN
Keywords: google image download extractor
Platform: UNKNOWN
Classifier: Development Status :: 4 - Beta
Classifier: Intended Audience :: Developers
Classifier: Topic :: Software Development :: Libraries
Classifier: License :: OSI Approved :: MIT License
Classifier: Programming Language :: Python :: 3.6
Requires-Dist: selenium
Requires-Dist: bs4
Requires-Dist: requests
Requires-Dist: termcolor
Requires-Dist: progressbar2
Requires-Dist: pillow
Requires-Dist: humanfriendly
